{
    "info": {
        "description": "AIHub Bus Passenger Dataset",
        "year": 2020,
        "version": "1.0",
        "img_path": "",
        "width": 1920,
        "height": 1080,
        "G-Sensor": "-21,12,1283",
        "Gyro": "0,0,0"
    },
    "annotations": [
        {
            "id": 0,
            "bbox": [
                1176,
                66,
                1285,
                386
            ],
            "occluded": true,
            "num_keypoints": 16,
            "keypoints": [
                1195,
                343,
                1,
                1205,
                261,
                1,
                1208,
                237,
                1,
                1262,
                231,
                2,
                1239,
                261,
                2,
                1267,
                345,
                2,
                1229,
                236,
                1,
                1222,
                162,
                2,
                1222,
                118,
                2,
                1219,
                100,
                2,
                1223,
                204,
                2,
                1197,
                196,
                1,
                1195,
                145,
                2,
                1259,
                141,
                2,
                1256,
                184,
                2,
                1230,
                225,
                2
            ],
            "action": "sit down",
            "age": "adult",
            "disabled": false,
            "mask": true,
            "get_on": false,
            "get_off": false
        },
        {
            "id": 1,
            "bbox": [
                1367,
                88,
                1658,
                657
            ],
            "occluded": true,
            "num_keypoints": 16,
            "keypoints": [
                1407,
                587,
                2,
                1386,
                482,
                2,
                1457,
                431,
                2,
                1564,
                430,
                1,
                1624,
                498,
                1,
                1585,
                606,
                1,
                1506,
                433,
                1,
                1501,
                276,
                2,
                1490,
                198,
                2,
                1488,
                144,
                2,
                1448,
                365,
                2,
                1409,
                320,
                2,
                1437,
                225,
                2,
                1566,
                220,
                2,
                1633,
                330,
                2,
                1574,
                272,
                2
            ],
            "action": "sit down",
            "age": "adult",
            "disabled": false,
            "mask": true,
            "get_on": false,
            "get_off": true
        }
    ]
}